{"name":"Infront Sports \u0026 Media","description":"Infront Sports \u0026 Media AG, a Zug, Switzerland-based international sports marketing companies.","website":"infrontsports.com","mattermark_score":"90","employees":"498","employees_month_ago":"487","employees_6_months_ago":"436","website_uniques":"5325","mobile_downloads":null,"stage":"exited (acquired)","total_funding":null,"last_funding_amount":null,"last_funding_date":null,"location":"zug","city":"Zug","state":null,"country":"che","twitter_handle":"infrontsports","facebook_handle":null,"linkedin_id":"63988","funding":[],"stories":[{"title":"Infront Acquires Majority Shareholding In Omnigon","url":"http://feedproxy.google.com/~r/SportTechie/~3/uxKbW7c8QQw/","date":"Jan 20 2016","source":"Sport Techie"},{"title":"Bridgepoint to sell Infront Sports \u0026 Media for $1.2 bln","url":"https://www.pehub.com/2015/02/bridgepoint-to-sell-infront-sports-media-for-1-2-bln/","date":"Feb 10 2015","source":"Reuters PEHub"},{"title":"Infront says reviewing options for the company","url":"http://feeds.reuters.com/~r/reuters/privateequityNews/~3/oD_XDWBKih8/story01.htm","date":"Sep 03 2014","source":"Reuters / Private Equity"}],"growth_scores":[{"recorded_at":"2017-01-22 00:00:00 +0000","score":"90"},{"recorded_at":"2017-01-15 00:00:00 +0000","score":"94"}],"mindshare_scores":[{"recorded_at":"2017-01-22 00:00:00 +0000","score":"90"},{"recorded_at":"2017-01-15 00:00:00 +0000","score":"94"}],"acquired_by":[{"event_id":1651,"closed_date":"2011-09-04","company_id":69179,"company_name":"Bridgepoint","company_domain":"bridgepoint.eu"}],"acquired_companies":[],"est_founding_date":"2003-06-01","business_models":null,"industries":["entertainment","marketing"],"mattermark_weekly_momentum":[{"recorded_at":"2017-01-22 00:00:00 +0000","score":"-586"},{"recorded_at":"2017-01-15 00:00:00 +0000","score":"-502"}],"employee_count":[{"recorded_at":"2015-11-10 15:00:00 +0000","score":"498"},{"recorded_at":"2015-05-24 02:23:57 +0000","score":"436"}],"alexa_rank":[{"recorded_at":"2017-01-17 18:11:47 +0000","score":"373807"},{"recorded_at":"2017-01-04 09:56:21 +0000","score":"340897"}],"facebook_talking_count":[],"facebook_like_count":[],"twitter_follower_count":[{"recorded_at":"2017-01-13 16:50:57 +0000","score":"8833"},{"recorded_at":"2017-01-02 10:11:06 +0000","score":"8760"}],"twitter_mentions":[],"linkedin_follower_count":[{"recorded_at":"2016-06-29 15:24:37 +0000","score":"12504"},{"recorded_at":"2016-02-25 19:06:38 +0000","score":"11169"}],"itunes_usa_weekly_download":[],"inbound_links":[{"recorded_at":"2016-02-26 19:25:47 +0000","score":"6"},{"recorded_at":"2016-01-29 23:46:43 +0000","score":"6"}],"est_monthly_uniques":[{"recorded_at":"2017-01-17 18:11:47 +0000","score":"19152"},{"recorded_at":"2017-01-04 09:56:21 +0000","score":"23517"}],"added_date":"2013-04-04 13:55:25","google_play_apps":[],"itunes_apps":[],"ipos":[]}