{"name":"InCrowd","description":"InCrowd partners with rights holders to build official mobile apps for fans. We provide real-time content, match analysis and gamification tools","website":"incrowdsports.com","mattermark_score":"89","employees":"20","employees_month_ago":"19","employees_6_months_ago":"15","website_uniques":null,"mobile_downloads":null,"stage":"pre series a","total_funding":"2390000","last_funding_amount":"2390000","last_funding_date":"2016-02-04","location":"london","city":"London","state":null,"country":"gbr","twitter_handle":"incrowd_sports","facebook_handle":null,"linkedin_id":"9291383","funding":[{"amount":"2390000","currency":"USD","series":"seed","funding_date":"2016-02-04","news_url":"http://www.unquote.com/uk/official-record/2445076/albion-leads-gbp165m-investment-in-incrowd","source":"derived","investor_ids":[4107],"investors":"Albion Ventures"}],"stories":[{"title":"For Doctors, the \"Trump Effect\" Is Strong Pessimism on Healthcare Costs, Access \u0026 Quality, while Believing Some Reforms Remain, Says Data from InCrowd","url":"http://www.marketwired.com/mw/release.do?id=2185968\u0026sourceType=3","date":"Jan 03 2017","source":"MarketWired"},{"title":"InCrowd Debuts MicroTracker, First Automated Approach To Life Science Market Research Tracking Studies","url":"http://www.prnewswire.com/news-releases/incrowd-debuts-microtracker-first-automated-approach-to-life-science-market-research-tracking-studies-300267415.html","date":"May 12 2016","source":"PR Newswire"},{"title":"InCrowd Pivoted From Disaster Communication Tool To Fan Engagement Platform","url":"http://feedproxy.google.com/~r/SportTechie/~3/kN10fKS3Lng/","date":"Feb 11 2016","source":"Sport Techie"},{"title":"InCrowd Sports Raises £1.65M in Funding","url":"http://www.finsmes.com/2016/02/incrowd-sports-raises-1-65m-in-funding.html","date":"Feb 05 2016","source":"FinSMEs"},{"title":"InCrowd expands to Alabama, believes in regional deal flow","url":"http://southernalpha.com/incrowd-expands-alabama-believes-regional-deal-flow/","date":"Dec 11 2014","source":"SouthernAlpha"},{"title":"InCrowd Raises $2.2M From Nauta Capital So That Your Doctor Can Take Marketing Surveys In Real-Time","url":"http://techcrunch.com/2012/09/06/incrowd-raises-2-2m-from-nauta-capital-so-that-your-doctor-can-take-marketing-surveys-in-real-time/","date":"Sep 06 2012","source":"Techcrunch"}],"growth_scores":[{"recorded_at":"2017-01-22 00:00:00 +0000","score":"129"},{"recorded_at":"2017-01-15 00:00:00 +0000","score":"129"}],"mindshare_scores":[{"recorded_at":"2017-01-22 00:00:00 +0000","score":"89"},{"recorded_at":"2017-01-15 00:00:00 +0000","score":"88"}],"acquired_by":[],"acquired_companies":[],"est_founding_date":"2015-01-01","business_models":["B2B"],"industries":["entertainment","mobile","software development"],"mattermark_weekly_momentum":[{"recorded_at":"2017-01-22 00:00:00 +0000","score":"138"},{"recorded_at":"2017-01-15 00:00:00 +0000","score":"148"}],"employee_count":[{"recorded_at":"2017-01-09 05:02:09 +0000","score":"20"},{"recorded_at":"2016-11-26 02:48:20 +0000","score":"18"}],"alexa_rank":[{"recorded_at":"2017-01-18 07:51:27 +0000","score":"2897984"},{"recorded_at":"2017-01-04 23:31:32 +0000","score":"3167870"}],"facebook_talking_count":[],"facebook_like_count":[],"twitter_follower_count":[{"recorded_at":"2017-01-23 06:25:30 +0000","score":"222"},{"recorded_at":"2017-01-08 16:55:46 +0000","score":"219"}],"twitter_mentions":[],"linkedin_follower_count":[{"recorded_at":"2015-12-25 19:46:13 +0000","score":"173"}],"itunes_usa_weekly_download":[],"inbound_links":[{"recorded_at":"2016-03-20 09:48:29 +0000","score":"0"},{"recorded_at":"2016-02-05 12:15:03 +0000","score":"0"}],"est_monthly_uniques":[{"recorded_at":"2017-01-18 07:51:27 +0000","score":"200"},{"recorded_at":"2017-01-04 23:31:32 +0000","score":"164"}],"added_date":"2016-02-05 11:56:02","google_play_apps":[],"itunes_apps":[],"ipos":[]}