{"name":"ClubReady","description":"ClubReady handles every aspect of healthclub management, from client wellness through to flexible billing options that let you choose the member billing options that suit you best.","website":"clubready.com","mattermark_score":"19","employees":"64","employees_month_ago":"62","employees_6_months_ago":"41","website_uniques":null,"mobile_downloads":null,"stage":"a","total_funding":"0","last_funding_amount":null,"last_funding_date":"2016-03-21","location":"st. louis","city":"St. Louis","state":"MO","country":"usa","twitter_handle":"ClubReadyStatus","facebook_handle":null,"linkedin_id":"2130858","funding":[{"amount":"","currency":"USD","series":"a","funding_date":"2016-03-21","news_url":"http://www.bioportfolio.com/news/article/2652652/ClubReady-Attracts-Private-Equity-Investment-to-Accelerate-Growth.html","source":"derived","investor_ids":[1000],"investors":"Level Equity"}],"stories":[{"title":"ClubReady raises Series A funding","url":"http://www.jcount.com/clubready-raises-series-funding/","date":"Mar 25 2016","source":"JCount"},{"title":"ClubReady Closes Series A Funding","url":"http://www.finsmes.com/2016/03/clubready-closes-series-a-funding.html","date":"Mar 22 2016","source":"FinSMEs"},{"title":"ClubReady Attracts Private Equity Investment to Accelerate Growth","url":"http://www.bioportfolio.com/news/article/2652652/ClubReady-Attracts-Private-Equity-Investment-to-Accelerate-Growth.html","date":"Mar 21 2016","source":"Bioportfolio"},{"title":"ClubReady Announces Series A Investment","url":"http://www.vcnewsdaily.com/clubready/venture-capital-funding/fhdtnqdzxs","date":null,"source":"VC News Daily"}],"growth_scores":[{"recorded_at":"2017-01-15 00:00:00 +0000","score":"184"},{"recorded_at":"2017-01-08 00:00:00 +0000","score":"186"}],"mindshare_scores":[{"recorded_at":"2017-01-15 00:00:00 +0000","score":"19"},{"recorded_at":"2017-01-08 00:00:00 +0000","score":"19"}],"acquired_by":[],"acquired_companies":[],"est_founding_date":"2004-01-01","business_models":["B2B"],"industries":["enterprise software","finance","fitness and wellness","payments"],"mattermark_weekly_momentum":[{"recorded_at":"2017-01-15 00:00:00 +0000","score":"46"},{"recorded_at":"2017-01-08 00:00:00 +0000","score":"61"}],"employee_count":[{"recorded_at":"2017-01-09 04:27:53 +0000","score":"64"},{"recorded_at":"2016-11-26 02:29:25 +0000","score":"61"}],"alexa_rank":[{"recorded_at":"2017-01-24 23:11:14 +0000","score":"132953"},{"recorded_at":"2017-01-11 05:31:23 +0000","score":"134700"}],"facebook_talking_count":[],"facebook_like_count":[],"twitter_follower_count":[{"recorded_at":"2017-01-20 22:52:38 +0000","score":"328"},{"recorded_at":"2017-01-07 19:46:40 +0000","score":"328"}],"twitter_mentions":[],"linkedin_follower_count":[{"recorded_at":"2016-12-26 10:40:58 +0000","score":"221"},{"recorded_at":"2016-04-23 20:12:26 +0000","score":"118"}],"itunes_usa_weekly_download":[],"inbound_links":[{"recorded_at":"2016-02-20 09:26:19 +0000","score":"12"},{"recorded_at":"2016-01-23 14:22:27 +0000","score":"7"}],"est_monthly_uniques":[{"recorded_at":"2017-01-24 23:11:14 +0000","score":"207213"},{"recorded_at":"2017-01-11 05:31:23 +0000","score":"205301"}],"added_date":"2015-10-19 16:51:41","google_play_apps":[],"itunes_apps":[],"ipos":[]}